CODE_OF_CONDUCT.md
CONTRIBUTING.md
LICENSE
humans.txt
sfdata_annexa_clean/__init__.py
sfdata_annexa_clean/__main__.py
sfdata_annexa_clean/annex_a/__init__.py
sfdata_annexa_clean/annex_a/cleaner.py
sfdata_annexa_clean/annex_a/custom_cleaner.py
sfdata_annexa_clean/annex_a/merger/__init__.py
sfdata_annexa_clean/annex_a/merger/configuration.py
sfdata_annexa_clean/annex_a/merger/file_scanner.py
sfdata_annexa_clean/annex_a/merger/matcher.py
sfdata_annexa_clean/annex_a/merger/matcher_report.py
sfdata_annexa_clean/annex_a/merger/workbook_util.py
sfdata_annexa_clean/annex_a/merger/workflow.py
sfdata_annexa_clean/assets/config/annex-a-merge.yml
sfdata_annexa_clean/assets/config/cin_datamap.yaml
sfdata_annexa_clean/assets/config/cin_to_annexa.yaml
sfdata_annexa_clean/assets/config/data-map.yml
sfdata_annexa_clean/config/__init__.py
sfdata_annexa_clean/datatables/__init__.py
sfdata_annexa_clean/datatables/cache.py
sfdata_annexa_clean/datatables/load.py
sfdata_annexa_clean/datatables/merge.py
sfdata_annexa_clean/datatables/normalise.py
sfdata_annexa_clean/log/__init__.py
sfdata_annexa_clean/log/annexa_log.py
sfdata_annexa_clean/log/cin_log.py
sfdata_annexa_clean/log/log.py
sfdata_annexa_clean/regex/__init__.py
sfdata_annexa_clean-0.1.1.dist-info/LICENSE
sfdata_annexa_clean-0.1.1.dist-info/WHEEL
sfdata_annexa_clean-0.1.1.dist-info/METADATA
sfdata_annexa_clean-0.1.1.dist-info/RECORD
