Metadata-Version: 2.1
Name: sfdata-annexa-clean
Version: 0.1.1
Summary: A cleaner module for Annex A Data
Home-page: https://github.com/CSCDP/sfdata-annexa-clean
License: MIT
Keywords: data,datascience,datawrangling,children's services,annex a
Author: Céline Gross
Author-email: celine.m.gross@gmail.com
Requires-Python: >=3.7.1,<4.0
Classifier: Development Status :: 4 - Beta
Classifier: Environment :: Console
Classifier: Intended Audience :: Developers
Classifier: Intended Audience :: Other Audience
Classifier: License :: OSI Approved :: MIT License
Classifier: Programming Language :: Python :: 3
Classifier: Programming Language :: Python :: 3.7
Classifier: Programming Language :: Python :: 3.8
Classifier: Programming Language :: Python :: 3.9
Requires-Dist: PyYAML (>=5.4.1,<6.0.0)
Requires-Dist: XlsxWriter (>=3.0.1,<4.0.0)
Requires-Dist: dacite (>=1.6.0,<2.0.0)
Requires-Dist: jupyterlab (>=3.1.17,<4.0.0)
Requires-Dist: openpyxl (>=3.0.9,<4.0.0)
Requires-Dist: pandas (>=1.3.3,<2.0.0)
Requires-Dist: xlrd (>=2.0.1,<3.0.0)
Project-URL: Repository, https://github.com/CSCDP/sfdata-annexa-clean
